{"id":"swsh12.5","nome":"Zenit Regale","totaleUfficiale":159,"totaleConSegrete":160,"scaricatoIl":"2026-07-19","carte":[{"numero":"001","nome":"Oddish","categoria":"Pokémon","rarita":"Comune","immagine":"https://assets.tcgdex.net/it/swsh/swsh12.5/001","stadio":"Base","evolveDa":null,"tipi":["Erba"],"ps":50,"ritirata":1,"attacchi":[{"nome":"Fogliamerang","costo":["Incolore"],"danno":"10×"}]},{"numero":"002","nome":"Gloom","categoria":"Pokémon","rarita":"Non comune","immagine":"https://assets.tcgdex.net/it/swsh/swsh12.5/002","stadio":"Livello 1","evolveDa":"Oddish","tipi":["Erba"],"ps":70,"ritirata":1,"attacchi":[{"nome":"Aroma Offensivo","costo":["Erba","Incolore"],"danno":20}]},{"numero":"003","nome":"Bellossom","categoria":"Pokémon","rarita":"Rara","immagine":"https://assets.tcgdex.net/it/swsh/swsh12.5/003","stadio":"Livello 2","evolveDa":"Gloom","tipi":["Erba"],"ps":120,"ritirata":1,"attacchi":[{"nome":"Fioregiro","costo":["Erba","Incolore"],"danno":"80×"}]},{"numero":"004","nome":"Tangela","categoria":"Pokémon","rarita":"Comune","immagine":"https://assets.tcgdex.net/it/swsh/swsh12.5/004","stadio":"Base","evolveDa":null,"tipi":["Erba"],"ps":80,"ritirata":2,"attacchi":[{"nome":"Battuta","costo":["Incolore"],"danno":10},{"nome":"Frustata","costo":["Erba","Erba","Incolore"],"danno":60}]},{"numero":"005","nome":"Tangrowth","categoria":"Pokémon","rarita":"Rara","immagine":"https://assets.tcgdex.net/it/swsh/swsh12.5/005","stadio":"Livello 1","evolveDa":"Tangela","tipi":["Erba"],"ps":150,"ritirata":4,"attacchi":[{"nome":"Liane Aspiranti","costo":["Erba","Incolore"],"danno":50},{"nome":"Martello","costo":["Erba","Erba","Incolore"],"danno":130}]},{"numero":"006","nome":"Scyther","categoria":"Pokémon","rarita":"Comune","immagine":"https://assets.tcgdex.net/it/swsh/swsh12.5/006","stadio":"Base","evolveDa":null,"tipi":["Erba"],"ps":80,"ritirata":1,"attacchi":[{"nome":"Taglio Mach","costo":["Incolore"],"danno":10}]},{"numero":"007","nome":"Sunkern","categoria":"Pokémon","rarita":"Comune","immagine":"https://assets.tcgdex.net/it/swsh/swsh12.5/007","stadio":"Base","evolveDa":null,"tipi":["Erba"],"ps":40,"ritirata":1,"attacchi":[{"nome":"Semebomba","costo":["Incolore","Incolore"],"danno":20}]},{"numero":"008","nome":"Yanma","categoria":"Pokémon","rarita":"Comune","immagine":"https://assets.tcgdex.net/it/swsh/swsh12.5/008","stadio":"Base","evolveDa":null,"tipi":["Erba"],"ps":70,"ritirata":1,"attacchi":[{"nome":"Volo Radente","costo":["Incolore"],"danno":null},{"nome":"Vento Tagliente","costo":["Incolore","Incolore","Incolore"],"danno":70}]},{"numero":"009","nome":"Yanmega","categoria":"Pokémon","rarita":"Rara","immagine":"https://assets.tcgdex.net/it/swsh/swsh12.5/009","stadio":"Livello 1","evolveDa":"Yanma","tipi":["Erba"],"ps":130,"ritirata":0,"attacchi":[{"nome":"Sparainmezzo","costo":["Incolore"],"danno":20},{"nome":"Ala Jet","costo":["Erba","Erba","Incolore"],"danno":160}]},{"numero":"010","nome":"Kricketot","categoria":"Pokémon","rarita":"Comune","immagine":"https://assets.tcgdex.net/it/swsh/swsh12.5/010","stadio":"Base","evolveDa":null,"tipi":["Erba"],"ps":60,"ritirata":1,"attacchi":[{"nome":"Inciampare","costo":["Erba"],"danno":"10+"}]},{"numero":"011","nome":"Cherubi","categoria":"Pokémon","rarita":"Comune","immagine":"https://assets.tcgdex.net/it/swsh/swsh12.5/011","stadio":"Base","evolveDa":null,"tipi":["Erba"],"ps":50,"ritirata":1,"attacchi":[{"nome":"Fogliame","costo":["Erba"],"danno":10}]},{"numero":"012","nome":"Carnivine","categoria":"Pokémon","rarita":"Non comune","immagine":"https://assets.tcgdex.net/it/swsh/swsh12.5/012","stadio":"Base","evolveDa":null,"tipi":["Erba"],"ps":90,"ritirata":1,"attacchi":[{"nome":"Saliva Infetta","costo":["Erba"],"danno":null},{"nome":"Legafermo","costo":["Incolore","Incolore"],"danno":40}]},{"numero":"013","nome":"Leafeon V","categoria":"Pokémon","rarita":"Olografica Rara V","immagine":"https://assets.tcgdex.net/it/swsh/swsh12.5/013","stadio":"Base","evolveDa":null,"tipi":["Erba"],"ps":210,"ritirata":2,"attacchi":[{"nome":"Fogliamanto","costo":["Erba"],"danno":30},{"nome":"Lacerattacco","costo":["Erba","Erba","Incolore"],"danno":180}]},{"numero":"014","nome":"Leafeon V ASTRO","categoria":"Pokémon","rarita":"Olografica Rara VSTAR","immagine":"https://assets.tcgdex.net/it/swsh/swsh12.5/014","stadio":"V ASTRO","evolveDa":"Leafeon-V","tipi":["Erba"],"ps":260,"ritirata":2,"attacchi":[{"nome":"Fogliamanto","costo":["Erba","Erba","Incolore"],"danno":180}]},{"numero":"015","nome":"Grubbin","categoria":"Pokémon","rarita":"Comune","immagine":"https://assets.tcgdex.net/it/swsh/swsh12.5/015","stadio":"Base","evolveDa":null,"tipi":["Erba"],"ps":70,"ritirata":2,"attacchi":[{"nome":"Energizza","costo":["Incolore"],"danno":null},{"nome":"Attacco a Sorpresa","costo":["Incolore","Incolore","Incolore"],"danno":50}]},{"numero":"016","nome":"Zarude","categoria":"Pokémon","rarita":"Olografica Rara","immagine":"https://assets.tcgdex.net/it/swsh/swsh12.5/016","stadio":"Base","evolveDa":null,"tipi":["Erba"],"ps":120,"ritirata":1,"attacchi":[{"nome":"Trascinato Via","costo":["Erba"],"danno":null},{"nome":"Triplafrustata","costo":["Erba","Erba"],"danno":"70×"}]},{"numero":"017","nome":"Calyrex","categoria":"Pokémon","rarita":"Olografica Rara","immagine":"https://assets.tcgdex.net/it/swsh/swsh12.5/017","stadio":"Base","evolveDa":null,"tipi":["Erba"],"ps":110,"ritirata":2,"attacchi":[{"nome":"Ordini del Re","costo":["Incolore","Incolore"],"danno":30},{"nome":"Fioritura Splendente","costo":["Erba","Incolore","Incolore"],"danno":90}]},{"numero":"018","nome":"Charizard V","categoria":"Pokémon","rarita":"Olografica Rara V","immagine":"https://assets.tcgdex.net/it/swsh/swsh12.5/018","stadio":"Base","evolveDa":null,"tipi":["Fuoco"],"ps":220,"ritirata":2,"attacchi":[{"nome":"Bruciatutto","costo":["Fuoco","Fuoco","Incolore"],"danno":90},{"nome":"Caldobomba","costo":["Fuoco","Fuoco","Fuoco","Incolore"],"danno":180}]},{"numero":"019","nome":"Charizard V ASTRO","categoria":"Pokémon","rarita":"Olografica Rara VSTAR","immagine":"https://assets.tcgdex.net/it/swsh/swsh12.5/019","stadio":"V ASTRO","evolveDa":"Charizard-V","tipi":["Fuoco"],"ps":280,"ritirata":2,"attacchi":[{"nome":"Fuoco Esplosivo","costo":["Fuoco","Fuoco","Incolore"],"danno":"130+"},{"nome":"Astro Fiammata","costo":["Fuoco","Fuoco","Fuoco","Incolore"],"danno":320}]},{"numero":"020","nome":"Charizard Lucente","categoria":"Pokémon","rarita":"Rara Lucente","immagine":"https://assets.tcgdex.net/it/swsh/swsh12.5/020","stadio":"Base","evolveDa":null,"tipi":["Fuoco"],"ps":160,"ritirata":3,"attacchi":[{"nome":"Combustibomba","costo":["Fuoco","Incolore","Incolore","Incolore","Incolore"],"danno":250}]},{"numero":"021","nome":"Entei","categoria":"Pokémon","rarita":"Olografica Rara","immagine":"https://assets.tcgdex.net/it/swsh/swsh12.5/021","stadio":"Base","evolveDa":null,"tipi":["Fuoco"],"ps":120,"ritirata":2,"attacchi":[{"nome":"Lacerartiglio","costo":["Incolore","Incolore","Incolore"],"danno":90}]},{"numero":"022","nome":"Simisear V","categoria":"Pokémon","rarita":"Olografica Rara V","immagine":"https://assets.tcgdex.net/it/swsh/swsh12.5/022","stadio":"Base","evolveDa":null,"tipi":["Fuoco"],"ps":210,"ritirata":1,"attacchi":[{"nome":"Potere Ustionante","costo":["Fuoco"],"danno":20},{"nome":"Giocoleria Fiammeggiante","costo":["Fuoco","Incolore","Incolore"],"danno":"90+"}]},{"numero":"023","nome":"Simisear V ASTRO","categoria":"Pokémon","rarita":"Olografica Rara VSTAR","immagine":"https://assets.tcgdex.net/it/swsh/swsh12.5/023","stadio":"V ASTRO","evolveDa":"Simisear-V","tipi":["Fuoco"],"ps":260,"ritirata":2,"attacchi":[{"nome":"Febbre Palladifuoco","costo":["Fuoco","Incolore","Incolore"],"danno":"40+"},{"nome":"Astro Sfavillante","costo":["Fuoco"],"danno":"30×"}]},{"numero":"024","nome":"Larvesta","categoria":"Pokémon","rarita":"Comune","immagine":"https://assets.tcgdex.net/it/swsh/swsh12.5/024","stadio":"Base","evolveDa":null,"tipi":["Fuoco"],"ps":80,"ritirata":3,"attacchi":[{"nome":"Carboni Ardenti","costo":["Fuoco"],"danno":20}]},{"numero":"025","nome":"Volcarona","categoria":"Pokémon","rarita":"Rara","immagine":"https://assets.tcgdex.net/it/swsh/swsh12.5/025","stadio":"Livello 1","evolveDa":"Larvesta","tipi":["Fuoco"],"ps":130,"ritirata":2,"attacchi":[{"nome":"Fuocofatuo","costo":["Fuoco"],"danno":40},{"nome":"Calore Vulcanico","costo":["Fuoco","Incolore"],"danno":120}]},{"numero":"026","nome":"Volcanion","categoria":"Pokémon","rarita":"Olografica Rara","immagine":"https://assets.tcgdex.net/it/swsh/swsh12.5/026","stadio":"Base","evolveDa":null,"tipi":["Fuoco"],"ps":130,"ritirata":3,"attacchi":[{"nome":"Martello","costo":["Incolore","Incolore"],"danno":30},{"nome":"Idroustione","costo":["Fuoco","Fuoco","Incolore"],"danno":"80+"}]},{"numero":"027","nome":"Salandit","categoria":"Pokémon","rarita":"Comune","immagine":"https://assets.tcgdex.net/it/swsh/swsh12.5/027","stadio":"Base","evolveDa":null,"tipi":["Fuoco"],"ps":70,"ritirata":1,"attacchi":[{"nome":"Cerca Famiglia","costo":["Incolore"],"danno":null},{"nome":"Graffio","costo":["Fuoco"],"danno":10}]},{"numero":"028","nome":"Salazzle","categoria":"Pokémon","rarita":"Non comune","immagine":"https://assets.tcgdex.net/it/swsh/swsh12.5/028","stadio":"Livello 1","evolveDa":"Salandit","tipi":["Fuoco"],"ps":120,"ritirata":1,"attacchi":[{"nome":"Confondicoda","costo":["Incolore"],"danno":20},{"nome":"Super Scottata","costo":["Fuoco","Incolore"],"danno":60}]},{"numero":"029","nome":"Seel","categoria":"Pokémon","rarita":"Comune","immagine":"https://assets.tcgdex.net/it/swsh/swsh12.5/029","stadio":"Base","evolveDa":null,"tipi":["Acqua"],"ps":70,"ritirata":1,"attacchi":[{"nome":"Bottintesta","costo":["Acqua"],"danno":10},{"nome":"Spruzzapioggia","costo":["Acqua","Incolore"],"danno":20}]},{"numero":"030","nome":"Mr. Mime di Galar","categoria":"Pokémon","rarita":"Comune","immagine":"https://assets.tcgdex.net/it/swsh/swsh12.5/030","stadio":"Base","evolveDa":null,"tipi":["Acqua"],"ps":80,"ritirata":1,"attacchi":[{"nome":"Botta","costo":["Acqua"],"danno":10},{"nome":"Cercatrova","costo":["Incolore","Incolore"],"danno":null}]},{"numero":"031","nome":"Wailmer","categoria":"Pokémon","rarita":"Comune","immagine":"https://assets.tcgdex.net/it/swsh/swsh12.5/031","stadio":"Base","evolveDa":null,"tipi":["Acqua"],"ps":120,"ritirata":3,"attacchi":[{"nome":"Pausa","costo":["Incolore"],"danno":null},{"nome":"Pistolacqua","costo":["Incolore","Incolore","Incolore"],"danno":70}]},{"numero":"032","nome":"Wailord","categoria":"Pokémon","rarita":"Rara","immagine":"https://assets.tcgdex.net/it/swsh/swsh12.5/032","stadio":"Livello 1","evolveDa":"Wailmer","tipi":["Acqua"],"ps":220,"ritirata":4,"attacchi":[{"nome":"Assorbibolla","costo":["Incolore","Incolore","Incolore"],"danno":80},{"nome":"Impatto Pesante","costo":["Acqua","Acqua","Incolore","Incolore","Incolore"],"danno":180}]},{"numero":"033","nome":"Corphish","categoria":"Pokémon","rarita":"Comune","immagine":"https://assets.tcgdex.net/it/swsh/swsh12.5/033","stadio":"Base","evolveDa":null,"tipi":["Acqua"],"ps":70,"ritirata":2,"attacchi":[{"nome":"Pistolacqua","costo":["Incolore"],"danno":10},{"nome":"Martellata","costo":["Acqua","Incolore","Incolore"],"danno":50}]},{"numero":"034","nome":"Snorunt","categoria":"Pokémon","rarita":"Comune","immagine":"https://assets.tcgdex.net/it/swsh/swsh12.5/034","stadio":"Base","evolveDa":null,"tipi":["Acqua"],"ps":60,"ritirata":1,"attacchi":[{"nome":"Bottintesta","costo":["Acqua","Incolore"],"danno":30}]},{"numero":"035","nome":"Luvdisc","categoria":"Pokémon","rarita":"Comune","immagine":"https://assets.tcgdex.net/it/swsh/swsh12.5/035","stadio":"Base","evolveDa":null,"tipi":["Acqua"],"ps":70,"ritirata":1,"attacchi":[{"nome":"Pesca Sentimentale","costo":["Acqua"],"danno":null},{"nome":"Azione","costo":["Incolore"],"danno":20}]},{"numero":"036","nome":"Kyogre","categoria":"Pokémon","rarita":"Olografica Rara","immagine":"https://assets.tcgdex.net/it/swsh/swsh12.5/036","stadio":"Base","evolveDa":null,"tipi":["Acqua"],"ps":140,"ritirata":3,"attacchi":[{"nome":"Radunonda","costo":["Incolore"],"danno":null},{"nome":"Onda Dinamica","costo":["Acqua","Acqua","Acqua","Incolore"],"danno":null}]},{"numero":"037","nome":"Kyogre V","categoria":"Pokémon","rarita":"Olografica Rara V","immagine":"https://assets.tcgdex.net/it/swsh/swsh12.5/037","stadio":"Base","evolveDa":null,"tipi":["Acqua"],"ps":230,"ritirata":3,"attacchi":[{"nome":"Doppiosplash","costo":["Acqua","Incolore","Incolore"],"danno":null},{"nome":"Idrotifone","costo":["Acqua","Incolore","Incolore","Incolore"],"danno":210}]},{"numero":"038","nome":"Glaceon V","categoria":"Pokémon","rarita":"Olografica Rara V","immagine":"https://assets.tcgdex.net/it/swsh/swsh12.5/038","stadio":"Base","evolveDa":null,"tipi":["Acqua"],"ps":210,"ritirata":2,"attacchi":[{"nome":"Gelocarica","costo":["Acqua"],"danno":30},{"nome":"Ventogelido","costo":["Acqua","Acqua","Incolore"],"danno":130}]},{"numero":"039","nome":"Shinx","categoria":"Pokémon","rarita":"Comune","immagine":"https://assets.tcgdex.net/it/swsh/swsh12.5/039","stadio":"Base","evolveDa":null,"tipi":["Lampo"],"ps":60,"ritirata":1,"attacchi":[{"nome":"Retrocalcio","costo":["Lampo"],"danno":20}]},{"numero":"040","nome":"Shinx","categoria":"Pokémon","rarita":"Comune","immagine":"https://assets.tcgdex.net/it/swsh/swsh12.5/040","stadio":"Base","evolveDa":null,"tipi":["Lampo"],"ps":60,"ritirata":1,"attacchi":[{"nome":"Scoppiotuono","costo":["Lampo"],"danno":30}]},{"numero":"041","nome":"Luxio","categoria":"Pokémon","rarita":"Non comune","immagine":"https://assets.tcgdex.net/it/swsh/swsh12.5/041","stadio":"Livello 1","evolveDa":"Shinx","tipi":["Lampo"],"ps":80,"ritirata":1,"attacchi":[{"nome":"Calcio Aereo","costo":["Lampo"],"danno":null},{"nome":"Zuccalampo","costo":["Lampo","Incolore"],"danno":50}]},{"numero":"042","nome":"Luxio","categoria":"Pokémon","rarita":"Non comune","immagine":"https://assets.tcgdex.net/it/swsh/swsh12.5/042","stadio":"Livello 1","evolveDa":"Shinx","tipi":["Lampo"],"ps":90,"ritirata":1,"attacchi":[{"nome":"Cortoscintilla","costo":["Lampo"],"danno":null},{"nome":"Morso","costo":["Lampo","Incolore"],"danno":40}]},{"numero":"043","nome":"Luxray","categoria":"Pokémon","rarita":"Rara","immagine":"https://assets.tcgdex.net/it/swsh/swsh12.5/043","stadio":"Livello 2","evolveDa":"Luxio","tipi":["Lampo"],"ps":150,"ritirata":1,"attacchi":[{"nome":"Elettropasso","costo":["Lampo"],"danno":null},{"nome":"Sfregiocolpi","costo":["Lampo","Incolore"],"danno":"100+"}]},{"numero":"044","nome":"Luxray","categoria":"Pokémon","rarita":"Rara","immagine":"https://assets.tcgdex.net/it/swsh/swsh12.5/044","stadio":"Livello 2","evolveDa":"Luxio","tipi":["Lampo"],"ps":160,"ritirata":0,"attacchi":[{"nome":"Zanna Esploratrice","costo":["Incolore"],"danno":50}]},{"numero":"045","nome":"Rotom V","categoria":"Pokémon","rarita":"Olografica Rara V","immagine":"https://assets.tcgdex.net/it/swsh/swsh12.5/045","stadio":"Base","evolveDa":null,"tipi":["Lampo"],"ps":190,"ritirata":1,"attacchi":[{"nome":"Cortoscarto","costo":["Lampo","Lampo"],"danno":"40+"}]},{"numero":"046","nome":"Rotom V ASTRO","categoria":"Pokémon","rarita":"Olografica Rara VSTAR","immagine":"https://assets.tcgdex.net/it/swsh/swsh12.5/046","stadio":"V ASTRO","evolveDa":"Rotom-V","tipi":["Lampo"],"ps":250,"ritirata":1,"attacchi":[{"nome":"Impulsoscarto","costo":["Lampo","Lampo"],"danno":"80+"}]},{"numero":"047","nome":"Emolga","categoria":"Pokémon","rarita":"Comune","immagine":"https://assets.tcgdex.net/it/swsh/swsh12.5/047","stadio":"Base","evolveDa":null,"tipi":["Lampo"],"ps":70,"ritirata":0,"attacchi":[{"nome":"Tuonoshock","costo":["Lampo"],"danno":30}]},{"numero":"048","nome":"Eelektrik","categoria":"Pokémon","rarita":"Non comune","immagine":"https://assets.tcgdex.net/it/swsh/swsh12.5/048","stadio":"Livello 1","evolveDa":"Tynamo","tipi":["Lampo"],"ps":80,"ritirata":2,"attacchi":[{"nome":"Shock Statico","costo":["Lampo"],"danno":30}]},{"numero":"049","nome":"Helioptile","categoria":"Pokémon","rarita":"Comune","immagine":"https://assets.tcgdex.net/it/swsh/swsh12.5/049","stadio":"Base","evolveDa":null,"tipi":["Lampo"],"ps":70,"ritirata":1,"attacchi":[{"nome":"Shock Statico","costo":["Lampo"],"danno":10},{"nome":"Retrocalcio","costo":["Incolore","Incolore"],"danno":20}]},{"numero":"050","nome":"Heliolisk","categoria":"Pokémon","rarita":"Rara","immagine":"https://assets.tcgdex.net/it/swsh/swsh12.5/050","stadio":"Livello 1","evolveDa":"Helioptile","tipi":["Lampo"],"ps":120,"ritirata":1,"attacchi":[{"nome":"Shock Statico","costo":["Lampo"],"danno":30},{"nome":"Sprizzalampo","costo":["Lampo","Incolore","Incolore"],"danno":150}]},{"numero":"051","nome":"Charjabug Lucente","categoria":"Pokémon","rarita":"Rara Lucente","immagine":"https://assets.tcgdex.net/it/swsh/swsh12.5/051","stadio":"Base","evolveDa":null,"tipi":["Lampo"],"ps":90,"ritirata":2,"attacchi":[{"nome":"Attacco Lineare","costo":["Lampo"],"danno":null}]},{"numero":"052","nome":"Zeraora","categoria":"Pokémon","rarita":"Rara","immagine":"https://assets.tcgdex.net/it/swsh/swsh12.5/052","stadio":"Base","evolveDa":null,"tipi":["Lampo"],"ps":120,"ritirata":1,"attacchi":[{"nome":"Sprizzalampo","costo":["Lampo","Incolore"],"danno":70}]},{"numero":"053","nome":"Zeraora V","categoria":"Pokémon","rarita":"Olografica Rara V","immagine":"https://assets.tcgdex.net/it/swsh/swsh12.5/053","stadio":"Base","evolveDa":null,"tipi":["Lampo"],"ps":210,"ritirata":1,"attacchi":[{"nome":"Lacerartiglio","costo":["Lampo","Incolore"],"danno":50},{"nome":"Fulmine Tonante","costo":["Lampo","Lampo","Incolore"],"danno":190}]},{"numero":"054","nome":"Zeraora VMAX","categoria":"Pokémon","rarita":"Olografica Rara VMAX","immagine":"https://assets.tcgdex.net/it/swsh/swsh12.5/054","stadio":"VMAX","evolveDa":"Zeraora-V","tipi":["Lampo"],"ps":320,"ritirata":2,"attacchi":[{"nome":"Impulso Reattivo","costo":["Lampo","Lampo"],"danno":"60×"},{"nome":"Dynacolpo","costo":["Lampo","Lampo","Incolore"],"danno":240}]},{"numero":"055","nome":"Zeraora V ASTRO","categoria":"Pokémon","rarita":"Olografica Rara VSTAR","immagine":"https://assets.tcgdex.net/it/swsh/swsh12.5/055","stadio":"V ASTRO","evolveDa":"Zeraora-V","tipi":["Lampo"],"ps":270,"ritirata":0,"attacchi":[{"nome":"Battuta Dirompente","costo":["Lampo","Lampo","Incolore"],"danno":190},{"nome":"Astro Tempesta Folgorante","costo":["Lampo","Lampo","Lampo","Incolore"],"danno":null}]},{"numero":"056","nome":"Pincurchin","categoria":"Pokémon","rarita":"Non comune","immagine":"https://assets.tcgdex.net/it/swsh/swsh12.5/056","stadio":"Base","evolveDa":null,"tipi":["Lampo"],"ps":80,"ritirata":1,"attacchi":[{"nome":"Cerca Famiglia","costo":["Incolore"],"danno":null},{"nome":"Capriole","costo":["Lampo","Incolore"],"danno":"30+"}]},{"numero":"057","nome":"Exeggcute","categoria":"Pokémon","rarita":"Comune","immagine":"https://assets.tcgdex.net/it/swsh/swsh12.5/057","stadio":"Base","evolveDa":null,"tipi":["Psico"],"ps":60,"ritirata":1,"attacchi":[{"nome":"Psico","costo":["Psico","Incolore"],"danno":20}]},{"numero":"058","nome":"Exeggutor","categoria":"Pokémon","rarita":"Rara","immagine":"https://assets.tcgdex.net/it/swsh/swsh12.5/058","stadio":"Livello 1","evolveDa":"Exeggcute","tipi":["Psico"],"ps":130,"ritirata":2,"attacchi":[{"nome":"Tempestona","costo":["Psico"],"danno":null},{"nome":"Fuggi Fuggi","costo":["Psico","Incolore","Incolore"],"danno":100}]},{"numero":"059","nome":"Mewtwo","categoria":"Pokémon","rarita":"Olografica Rara","immagine":"https://assets.tcgdex.net/it/swsh/swsh12.5/059","stadio":"Base","evolveDa":null,"tipi":["Psico"],"ps":130,"ritirata":2,"attacchi":[{"nome":"Psicopompa","costo":["Incolore"],"danno":null},{"nome":"Frangilimite","costo":["Psico","Psico","Incolore"],"danno":"90+"}]},{"numero":"060","nome":"Mew V","categoria":"Pokémon","rarita":"Olografica Rara V","immagine":"https://assets.tcgdex.net/it/swsh/swsh12.5/060","stadio":"Base","evolveDa":null,"tipi":["Psico"],"ps":180,"ritirata":0,"attacchi":[{"nome":"Miscuglio di Energia","costo":["Psico"],"danno":null},{"nome":"Guizzo Psichico","costo":["Psico","Incolore"],"danno":70}]},{"numero":"061","nome":"Girafarig","categoria":"Pokémon","rarita":"Non comune","immagine":"https://assets.tcgdex.net/it/swsh/swsh12.5/061","stadio":"Base","evolveDa":null,"tipi":["Psico"],"ps":90,"ritirata":1,"attacchi":[{"nome":"Pescata Doppia","costo":["Incolore"],"danno":null},{"nome":"Psicoraggio","costo":["Psico","Incolore"],"danno":30}]},{"numero":"062","nome":"Lunatone","categoria":"Pokémon","rarita":"Non comune","immagine":"https://assets.tcgdex.net/it/swsh/swsh12.5/062","stadio":"Base","evolveDa":null,"tipi":["Psico"],"ps":90,"ritirata":1,"attacchi":[{"nome":"Pesca Ciclica","costo":["Psico"],"danno":null},{"nome":"Lunacinesi","costo":["Incolore","Incolore","Incolore"],"danno":"30+"}]},{"numero":"063","nome":"Dusclops","categoria":"Pokémon","rarita":"Non comune","immagine":"https://assets.tcgdex.net/it/swsh/swsh12.5/063","stadio":"Livello 1","evolveDa":"Duskull","tipi":["Psico"],"ps":90,"ritirata":2,"attacchi":[{"nome":"Svanire nel Buio","costo":["Psico"],"danno":30}]},{"numero":"064","nome":"Tapu Lele","categoria":"Pokémon","rarita":"Olografica Rara","immagine":"https://assets.tcgdex.net/it/swsh/swsh12.5/064","stadio":"Base","evolveDa":null,"tipi":["Psico"],"ps":110,"ritirata":1,"attacchi":[{"nome":"Energiscoppio","costo":["Incolore","Incolore"],"danno":"20×"},{"nome":"Assorbimento Spirale","costo":["Psico","Psico","Incolore"],"danno":100}]},{"numero":"065","nome":"Hatterene V","categoria":"Pokémon","rarita":"Olografica Rara V","immagine":"https://assets.tcgdex.net/it/swsh/swsh12.5/065","stadio":"Base","evolveDa":null,"tipi":["Psico"],"ps":200,"ritirata":2,"attacchi":[{"nome":"Oroscopo","costo":["Psico"],"danno":null},{"nome":"Scoppio Teletrasporto","costo":["Psico","Incolore","Incolore"],"danno":80}]},{"numero":"066","nome":"Hatterene VMAX","categoria":"Pokémon","rarita":"Olografica Rara VMAX","immagine":"https://assets.tcgdex.net/it/swsh/swsh12.5/066","stadio":"VMAX","evolveDa":"Hatterene-V","tipi":["Psico"],"ps":320,"ritirata":2,"attacchi":[{"nome":"Gigacastigo","costo":["Psico","Incolore","Incolore"],"danno":150}]},{"numero":"067","nome":"Enamorus","categoria":"Pokémon","rarita":"Rara","immagine":"https://assets.tcgdex.net/it/swsh/swsh12.5/067","stadio":"Base","evolveDa":null,"tipi":["Psico"],"ps":120,"ritirata":2,"attacchi":[{"nome":"Assorbibacio","costo":["Psico"],"danno":20},{"nome":"Empatia Amorosa","costo":["Psico","Incolore","Incolore"],"danno":"70+"}]},{"numero":"068","nome":"Graveler","categoria":"Pokémon","rarita":"Non comune","immagine":"https://assets.tcgdex.net/it/swsh/swsh12.5/068","stadio":"Livello 1","evolveDa":"Geodude","tipi":["Lotta"],"ps":110,"ritirata":4,"attacchi":[{"nome":"Azione","costo":["Lotta"],"danno":30},{"nome":"Macignata","costo":["Lotta","Incolore","Incolore"],"danno":70}]},{"numero":"069","nome":"Solrock","categoria":"Pokémon","rarita":"Non comune","immagine":"https://assets.tcgdex.net/it/swsh/swsh12.5/069","stadio":"Base","evolveDa":null,"tipi":["Lotta"],"ps":90,"ritirata":1,"attacchi":[{"nome":"Attacco Rotante","costo":["Lotta","Incolore"],"danno":50}]},{"numero":"070","nome":"Baltoy","categoria":"Pokémon","rarita":"Comune","immagine":"https://assets.tcgdex.net/it/swsh/swsh12.5/070","stadio":"Base","evolveDa":null,"tipi":["Lotta"],"ps":60,"ritirata":1,"attacchi":[{"nome":"Schiaffo","costo":["Incolore","Incolore"],"danno":20}]},{"numero":"071","nome":"Riolu","categoria":"Pokémon","rarita":"Comune","immagine":"https://assets.tcgdex.net/it/swsh/swsh12.5/071","stadio":"Base","evolveDa":null,"tipi":["Lotta"],"ps":60,"ritirata":1,"attacchi":[{"nome":"Colpo Basso","costo":["Lotta","Lotta"],"danno":50}]},{"numero":"072","nome":"Pancham","categoria":"Pokémon","rarita":"Comune","immagine":"https://assets.tcgdex.net/it/swsh/swsh12.5/072","stadio":"Base","evolveDa":null,"tipi":["Lotta"],"ps":70,"ritirata":2,"attacchi":[{"nome":"Ceffone","costo":["Incolore","Incolore"],"danno":30}]},{"numero":"073","nome":"Rockruff","categoria":"Pokémon","rarita":"Comune","immagine":"https://assets.tcgdex.net/it/swsh/swsh12.5/073","stadio":"Base","evolveDa":null,"tipi":["Lotta"],"ps":60,"ritirata":1,"attacchi":[{"nome":"Vienifuori","costo":["Incolore"],"danno":null},{"nome":"Calcio Esplosivo","costo":["Lotta","Incolore"],"danno":20}]},{"numero":"074","nome":"Lycanroc","categoria":"Pokémon","rarita":"Rara","immagine":"https://assets.tcgdex.net/it/swsh/swsh12.5/074","stadio":"Livello 1","evolveDa":"Rockruff","tipi":["Lotta"],"ps":120,"ritirata":1,"attacchi":[{"nome":"Zanna della Notte","costo":["Lotta","Incolore"],"danno":"240-"}]},{"numero":"075","nome":"Koffing","categoria":"Pokémon","rarita":"Comune","immagine":"https://assets.tcgdex.net/it/swsh/swsh12.5/075","stadio":"Base","evolveDa":null,"tipi":["Oscurità"],"ps":70,"ritirata":1,"attacchi":[{"nome":"Smog","costo":["Oscurità","Incolore"],"danno":20}]},{"numero":"076","nome":"Absol","categoria":"Pokémon","rarita":"Olografica Rara","immagine":"https://assets.tcgdex.net/it/swsh/swsh12.5/076","stadio":"Base","evolveDa":null,"tipi":["Oscurità"],"ps":100,"ritirata":1,"attacchi":[{"nome":"Lacerazione","costo":["Oscurità"],"danno":30},{"nome":"Artiglio Perduto","costo":["Oscurità","Incolore","Incolore"],"danno":70}]},{"numero":"077","nome":"Purrloin","categoria":"Pokémon","rarita":"Comune","immagine":"https://assets.tcgdex.net/it/swsh/swsh12.5/077","stadio":"Base","evolveDa":null,"tipi":["Oscurità"],"ps":60,"ritirata":1,"attacchi":[{"nome":"Sfuriate","costo":["Incolore"],"danno":"10×"}]},{"numero":"078","nome":"Liepard","categoria":"Pokémon","rarita":"Rara","immagine":"https://assets.tcgdex.net/it/swsh/swsh12.5/078","stadio":"Livello 1","evolveDa":"Purrloin","tipi":["Oscurità"],"ps":100,"ritirata":1,"attacchi":[{"nome":"Sfuriate","costo":["Incolore","Incolore"],"danno":"40×"},{"nome":"Lacerartiglio","costo":["Oscurità","Oscurità","Incolore"],"danno":110}]},{"numero":"079","nome":"Krokorok","categoria":"Pokémon","rarita":"Non comune","immagine":"https://assets.tcgdex.net/it/swsh/swsh12.5/079","stadio":"Livello 1","evolveDa":"Sandile","tipi":["Oscurità"],"ps":90,"ritirata":2,"attacchi":[{"nome":"Morso","costo":["Oscurità"],"danno":20},{"nome":"Dragaggio","costo":["Incolore","Incolore","Incolore"],"danno":null}]},{"numero":"080","nome":"Pangoro","categoria":"Pokémon","rarita":"Rara","immagine":"https://assets.tcgdex.net/it/swsh/swsh12.5/080","stadio":"Livello 1","evolveDa":"Pancham","tipi":["Oscurità"],"ps":140,"ritirata":3,"attacchi":[{"nome":"Pugno Rotante","costo":["Oscurità","Incolore"],"danno":60},{"nome":"Azionferoce","costo":["Oscurità","Oscurità","Incolore"],"danno":160}]},{"numero":"081","nome":"Skrelp","categoria":"Pokémon","rarita":"Comune","immagine":"https://assets.tcgdex.net/it/swsh/swsh12.5/081","stadio":"Base","evolveDa":null,"tipi":["Oscurità"],"ps":60,"ritirata":1,"attacchi":[{"nome":"Azione","costo":["Oscurità"],"danno":10},{"nome":"Liquefazione","costo":["Oscurità","Incolore"],"danno":20}]},{"numero":"082","nome":"Dragalge","categoria":"Pokémon","rarita":"Rara","immagine":"https://assets.tcgdex.net/it/swsh/swsh12.5/082","stadio":"Livello 1","evolveDa":"Skrelp","tipi":["Oscurità"],"ps":120,"ritirata":1,"attacchi":[{"nome":"Velenorazzo","costo":["Oscurità"],"danno":null},{"nome":"Pinnalama","costo":["Oscurità","Incolore"],"danno":60}]},{"numero":"083","nome":"Hoopa","categoria":"Pokémon","rarita":"Olografica Rara","immagine":"https://assets.tcgdex.net/it/swsh/swsh12.5/083","stadio":"Base","evolveDa":null,"tipi":["Oscurità"],"ps":120,"ritirata":2,"attacchi":[{"nome":"Portaleassalto","costo":["Oscurità"],"danno":90}]},{"numero":"084","nome":"Meowth di Galar","categoria":"Pokémon","rarita":"Comune","immagine":"https://assets.tcgdex.net/it/swsh/swsh12.5/084","stadio":"Base","evolveDa":null,"tipi":["Metallo"],"ps":70,"ritirata":1,"attacchi":[{"nome":"Serrartigli","costo":["Metallo"],"danno":"10+"}]},{"numero":"085","nome":"Perrserker di Galar","categoria":"Pokémon","rarita":"Rara","immagine":"https://assets.tcgdex.net/it/swsh/swsh12.5/085","stadio":"Livello 1","evolveDa":"Meowth di Galar","tipi":["Metallo"],"ps":120,"ritirata":2,"attacchi":[{"nome":"Artigli Affilati","costo":["Metallo","Incolore"],"danno":"30+"},{"nome":"Lacerazione","costo":["Metallo","Incolore","Incolore"],"danno":90}]},{"numero":"086","nome":"Scizor","categoria":"Pokémon","rarita":"Rara","immagine":"https://assets.tcgdex.net/it/swsh/swsh12.5/086","stadio":"Livello 1","evolveDa":"Scyther","tipi":["Metallo"],"ps":130,"ritirata":2,"attacchi":[{"nome":"Forbice X","costo":["Incolore"],"danno":"30+"},{"nome":"Artigli Pericolosi","costo":["Incolore","Incolore","Incolore"],"danno":"80+"}]},{"numero":"087","nome":"Aron","categoria":"Pokémon","rarita":"Comune","immagine":"https://assets.tcgdex.net/it/swsh/swsh12.5/087","stadio":"Base","evolveDa":null,"tipi":["Metallo"],"ps":70,"ritirata":2,"attacchi":[{"nome":"Carica","costo":["Metallo"],"danno":10},{"nome":"Coinvolgimento","costo":["Incolore","Incolore"],"danno":30}]},{"numero":"088","nome":"Lairon","categoria":"Pokémon","rarita":"Non comune","immagine":"https://assets.tcgdex.net/it/swsh/swsh12.5/088","stadio":"Livello 1","evolveDa":"Aron","tipi":["Metallo"],"ps":90,"ritirata":3,"attacchi":[{"nome":"Confronto","costo":["Incolore","Incolore"],"danno":40},{"nome":"Scombussolare","costo":["Metallo","Metallo","Incolore","Incolore"],"danno":80}]},{"numero":"089","nome":"Aggron","categoria":"Pokémon","rarita":"Olografica Rara","immagine":"https://assets.tcgdex.net/it/swsh/swsh12.5/089","stadio":"Livello 2","evolveDa":"Lairon","tipi":["Metallo"],"ps":180,"ritirata":4,"attacchi":[{"nome":"Contropressa","costo":["Metallo","Incolore","Incolore"],"danno":90},{"nome":"Impatto Pesante","costo":["Metallo","Metallo","Incolore","Incolore"],"danno":180}]},{"numero":"090","nome":"Metang","categoria":"Pokémon","rarita":"Non comune","immagine":"https://assets.tcgdex.net/it/swsh/swsh12.5/090","stadio":"Livello 1","evolveDa":"Beldum","tipi":["Metallo"],"ps":100,"ritirata":2,"attacchi":[{"nome":"Pugnoscarica","costo":["Metallo","Incolore"],"danno":"30+"}]},{"numero":"091","nome":"Pawniard","categoria":"Pokémon","rarita":"Comune","immagine":"https://assets.tcgdex.net/it/swsh/swsh12.5/091","stadio":"Base","evolveDa":null,"tipi":["Metallo"],"ps":60,"ritirata":1,"attacchi":[{"nome":"Carica Avventata","costo":["Metallo"],"danno":30}]},{"numero":"092","nome":"Pawniard","categoria":"Pokémon","rarita":"Comune","immagine":"https://assets.tcgdex.net/it/swsh/swsh12.5/092","stadio":"Base","evolveDa":null,"tipi":["Metallo"],"ps":70,"ritirata":1,"attacchi":[{"nome":"Perforare","costo":["Metallo"],"danno":20}]},{"numero":"093","nome":"Bisharp","categoria":"Pokémon","rarita":"Non comune","immagine":"https://assets.tcgdex.net/it/swsh/swsh12.5/093","stadio":"Livello 1","evolveDa":"Pawniard","tipi":["Metallo"],"ps":110,"ritirata":1,"attacchi":[{"nome":"Battipesca","costo":["Incolore"],"danno":20},{"nome":"Colpotente","costo":["Metallo","Incolore"],"danno":70}]},{"numero":"094","nome":"Zacian","categoria":"Pokémon","rarita":"Olografica Rara","immagine":"https://assets.tcgdex.net/it/swsh/swsh12.5/094","stadio":"Base","evolveDa":null,"tipi":["Metallo"],"ps":130,"ritirata":2,"attacchi":[{"nome":"Legione d'Assalto","costo":["Metallo"],"danno":"20+"},{"nome":"Affettalama","costo":["Metallo","Incolore","Incolore"],"danno":100}]},{"numero":"095","nome":"Zacian V","categoria":"Pokémon","rarita":"Olografica Rara V","immagine":"https://assets.tcgdex.net/it/swsh/swsh12.5/095","stadio":"Base","evolveDa":null,"tipi":["Metallo"],"ps":220,"ritirata":2,"attacchi":[{"nome":"Perforacolpo","costo":["Metallo"],"danno":40},{"nome":"Taglio Maestoso","costo":["Metallo","Metallo","Incolore"],"danno":"100+"}]},{"numero":"096","nome":"Zacian V ASTRO","categoria":"Pokémon","rarita":"Olografica Rara VSTAR","immagine":"https://assets.tcgdex.net/it/swsh/swsh12.5/096","stadio":"V ASTRO","evolveDa":"Zacian-V","tipi":["Metallo"],"ps":270,"ritirata":2,"attacchi":[{"nome":"Frangilama","costo":["Metallo","Metallo","Incolore"],"danno":200},{"nome":"Astro Spada","costo":["Metallo","Metallo","Incolore","Incolore"],"danno":310}]},{"numero":"097","nome":"Zamazenta","categoria":"Pokémon","rarita":"Olografica Rara","immagine":"https://assets.tcgdex.net/it/swsh/swsh12.5/097","stadio":"Base","evolveDa":null,"tipi":["Metallo"],"ps":130,"ritirata":2,"attacchi":[{"nome":"Nemesi","costo":["Metallo","Metallo","Incolore"],"danno":"100+"}]},{"numero":"098","nome":"Zamazenta V","categoria":"Pokémon","rarita":"Olografica Rara V","immagine":"https://assets.tcgdex.net/it/swsh/swsh12.5/098","stadio":"Base","evolveDa":null,"tipi":["Metallo"],"ps":220,"ritirata":2,"attacchi":[{"nome":"Vendicabomba","costo":["Metallo","Incolore","Incolore"],"danno":"120+"}]},{"numero":"099","nome":"Zamazenta V ASTRO","categoria":"Pokémon","rarita":"Olografica Rara VSTAR","immagine":"https://assets.tcgdex.net/it/swsh/swsh12.5/099","stadio":"V ASTRO","evolveDa":"Zamazenta-V","tipi":["Metallo"],"ps":270,"ritirata":2,"attacchi":[{"nome":"Gigaimpatto","costo":["Metallo","Metallo","Incolore"],"danno":220}]},{"numero":"100","nome":"Rayquaza V","categoria":"Pokémon","rarita":"Olografica Rara V","immagine":"https://assets.tcgdex.net/it/swsh/swsh12.5/100","stadio":"Base","evolveDa":null,"tipi":["Drago"],"ps":210,"ritirata":2,"attacchi":[{"nome":"Dragopulsar","costo":["Lampo"],"danno":40},{"nome":"Spiralscoppio","costo":["Fuoco","Lampo"],"danno":"20+"}]},{"numero":"101","nome":"Rayquaza VMAX","categoria":"Pokémon","rarita":"Olografica Rara VMAX","immagine":"https://assets.tcgdex.net/it/swsh/swsh12.5/101","stadio":"VMAX","evolveDa":"Rayquaza-V","tipi":["Drago"],"ps":320,"ritirata":2,"attacchi":[{"nome":"Dynascoppio","costo":["Fuoco","Lampo"],"danno":"20+"}]},{"numero":"102","nome":"Rayquaza VMAX","categoria":"Pokémon","rarita":"Ultrarara","immagine":"https://assets.tcgdex.net/it/swsh/swsh12.5/102","stadio":"VMAX","evolveDa":"Rayquaza-V","tipi":["Drago"],"ps":320,"ritirata":2,"attacchi":[{"nome":"Dynascoppio","costo":["Fuoco","Lampo"],"danno":"20+"}]},{"numero":"103","nome":"Duraludon V","categoria":"Pokémon","rarita":"Olografica Rara V","immagine":"https://assets.tcgdex.net/it/swsh/swsh12.5/103","stadio":"Base","evolveDa":null,"tipi":["Drago"],"ps":220,"ritirata":2,"attacchi":[{"nome":"Ferrartigli","costo":["Lotta","Metallo"],"danno":70},{"nome":"Vastoimpatto","costo":["Lotta","Metallo","Metallo"],"danno":140}]},{"numero":"104","nome":"Duraludon VMAX","categoria":"Pokémon","rarita":"Olografica Rara VMAX","immagine":"https://assets.tcgdex.net/it/swsh/swsh12.5/104","stadio":"VMAX","evolveDa":"Duraludon-V","tipi":["Drago"],"ps":330,"ritirata":3,"attacchi":[{"nome":"Gigapolverizzazione","costo":["Lotta","Metallo","Metallo"],"danno":220}]},{"numero":"105","nome":"Eternatus Lucente","categoria":"Pokémon","rarita":"Rara Lucente","immagine":"https://assets.tcgdex.net/it/swsh/swsh12.5/105","stadio":"Base","evolveDa":null,"tipi":["Drago"],"ps":170,"ritirata":2,"attacchi":[{"nome":"Raggiopotenza","costo":["Fuoco","Oscurità","Incolore"],"danno":200}]},{"numero":"106","nome":"Tauros","categoria":"Pokémon","rarita":"Rara","immagine":"https://assets.tcgdex.net/it/swsh/swsh12.5/106","stadio":"Base","evolveDa":null,"tipi":["Incolore"],"ps":110,"ritirata":2,"attacchi":[{"nome":"Calcio Esplosivo","costo":["Incolore","Incolore"],"danno":30},{"nome":"Azione Adrenalinica","costo":["Incolore","Incolore","Incolore"],"danno":null}]},{"numero":"107","nome":"Ditto","categoria":"Pokémon","rarita":"Olografica Rara","immagine":"https://assets.tcgdex.net/it/swsh/swsh12.5/107","stadio":"Base","evolveDa":null,"tipi":["Incolore"],"ps":70,"ritirata":1,"attacchi":[]},{"numero":"108","nome":"Eevee V","categoria":"Pokémon","rarita":"Olografica Rara V","immagine":"https://assets.tcgdex.net/it/swsh/swsh12.5/108","stadio":"Base","evolveDa":null,"tipi":["Incolore"],"ps":200,"ritirata":1,"attacchi":[{"nome":"Azione","costo":["Incolore"],"danno":30},{"nome":"Audace V","costo":["Incolore","Incolore","Incolore"],"danno":"80+"}]},{"numero":"109","nome":"Snorlax","categoria":"Pokémon","rarita":"Rara","immagine":"https://assets.tcgdex.net/it/swsh/swsh12.5/109","stadio":"Base","evolveDa":null,"tipi":["Incolore"],"ps":160,"ritirata":3,"attacchi":[{"nome":"Impatto Pesante","costo":["Incolore","Incolore","Incolore"],"danno":80}]},{"numero":"110","nome":"Starly","categoria":"Pokémon","rarita":"Comune","immagine":"https://assets.tcgdex.net/it/swsh/swsh12.5/110","stadio":"Base","evolveDa":null,"tipi":["Incolore"],"ps":60,"ritirata":1,"attacchi":[{"nome":"Artiglio","costo":["Incolore"],"danno":30}]},{"numero":"111","nome":"Bidoof","categoria":"Pokémon","rarita":"Comune","immagine":"https://assets.tcgdex.net/it/swsh/swsh12.5/111","stadio":"Base","evolveDa":null,"tipi":["Incolore"],"ps":60,"ritirata":1,"attacchi":[{"nome":"Iperzanna","costo":["Incolore","Incolore"],"danno":30}]},{"numero":"112","nome":"Chatot","categoria":"Pokémon","rarita":"Comune","immagine":"https://assets.tcgdex.net/it/swsh/swsh12.5/112","stadio":"Base","evolveDa":null,"tipi":["Incolore"],"ps":70,"ritirata":0,"attacchi":[{"nome":"Pesca Ciclica","costo":["Incolore"],"danno":null},{"nome":"Alabattito","costo":["Incolore"],"danno":10}]},{"numero":"113","nome":"Regigigas V","categoria":"Pokémon","rarita":"Olografica Rara V","immagine":"https://assets.tcgdex.net/it/swsh/swsh12.5/113","stadio":"Base","evolveDa":null,"tipi":["Incolore"],"ps":240,"ritirata":4,"attacchi":[{"nome":"Martello","costo":["Incolore","Incolore"],"danno":50},{"nome":"Randellata Furiosa","costo":["Incolore","Incolore","Incolore"],"danno":"100+"}]},{"numero":"114","nome":"Regigigas V ASTRO","categoria":"Pokémon","rarita":"Olografica Rara VSTAR","immagine":"https://assets.tcgdex.net/it/swsh/swsh12.5/114","stadio":"V ASTRO","evolveDa":"Regigigas-V","tipi":["Incolore"],"ps":300,"ritirata":4,"attacchi":[{"nome":"Gigaimpatto","costo":["Incolore","Incolore","Incolore"],"danno":230}]},{"numero":"115","nome":"Shaymin","categoria":"Pokémon","rarita":"Non comune","immagine":"https://assets.tcgdex.net/it/swsh/swsh12.5/115","stadio":"Base","evolveDa":null,"tipi":["Incolore"],"ps":70,"ritirata":1,"attacchi":[{"nome":"Coglifiori","costo":["Incolore"],"danno":null},{"nome":"Retrocalcio","costo":["Incolore","Incolore"],"danno":30}]},{"numero":"116","nome":"Stoutland V","categoria":"Pokémon","rarita":"Olografica Rara V","immagine":"https://assets.tcgdex.net/it/swsh/swsh12.5/116","stadio":"Base","evolveDa":null,"tipi":["Incolore"],"ps":210,"ritirata":3,"attacchi":[{"nome":"Zanne Ingorde","costo":["Incolore","Incolore","Incolore"],"danno":40},{"nome":"Azionferoce","costo":["Incolore","Incolore","Incolore","Incolore"],"danno":200}]},{"numero":"117","nome":"Yungoos","categoria":"Pokémon","rarita":"Comune","immagine":"https://assets.tcgdex.net/it/swsh/swsh12.5/117","stadio":"Base","evolveDa":null,"tipi":["Incolore"],"ps":70,"ritirata":1,"attacchi":[{"nome":"Zannaffilata","costo":["Incolore"],"danno":20}]},{"numero":"118","nome":"Gumshoos","categoria":"Pokémon","rarita":"Rara","immagine":"https://assets.tcgdex.net/it/swsh/swsh12.5/118","stadio":"Livello 1","evolveDa":"Yungoos","tipi":["Incolore"],"ps":120,"ritirata":1,"attacchi":[{"nome":"Testata di Sorveglianza","costo":["Incolore","Incolore"],"danno":"30+"},{"nome":"Affondo Lungo","costo":["Incolore","Incolore"],"danno":60}]},{"numero":"119","nome":"Oranguru","categoria":"Pokémon","rarita":"Rara","immagine":"https://assets.tcgdex.net/it/swsh/swsh12.5/119","stadio":"Base","evolveDa":null,"tipi":["Incolore"],"ps":110,"ritirata":2,"attacchi":[{"nome":"Messinscena del Primate","costo":["Incolore"],"danno":null},{"nome":"Martello","costo":["Incolore","Incolore","Incolore"],"danno":70}]},{"numero":"120","nome":"Greedent V","categoria":"Pokémon","rarita":"Olografica Rara V","immagine":"https://assets.tcgdex.net/it/swsh/swsh12.5/120","stadio":"Base","evolveDa":null,"tipi":["Incolore"],"ps":210,"ritirata":2,"attacchi":[{"nome":"Corposcontro","costo":["Incolore","Incolore"],"danno":40},{"nome":"Incisivi Masticanti","costo":["Incolore","Incolore","Incolore"],"danno":120}]},{"numero":"121","nome":"Wooloo","categoria":"Pokémon","rarita":"Comune","immagine":"https://assets.tcgdex.net/it/swsh/swsh12.5/121","stadio":"Base","evolveDa":null,"tipi":["Incolore"],"ps":70,"ritirata":1,"attacchi":[{"nome":"Rotolamento Ruzzolante","costo":["Incolore"],"danno":"30×"}]},{"numero":"122","nome":"Dubwool","categoria":"Pokémon","rarita":"Rara","immagine":"https://assets.tcgdex.net/it/swsh/swsh12.5/122","stadio":"Livello 1","evolveDa":"Wooloo","tipi":["Incolore"],"ps":120,"ritirata":1,"attacchi":[{"nome":"Lancindietro","costo":["Incolore"],"danno":40},{"nome":"Carica Ruzzolante","costo":["Incolore","Incolore"],"danno":"60+"}]},{"numero":"123","nome":"Fabia","categoria":"Allenatore","rarita":"Olografica Rara","immagine":"https://assets.tcgdex.net/it/swsh/swsh12.5/123"},{"numero":"124","nome":"Beet","categoria":"Allenatore","rarita":"Olografica Rara","immagine":"https://assets.tcgdex.net/it/swsh/swsh12.5/124"},{"numero":"125","nome":"Martello Dirompente","categoria":"Allenatore","rarita":"Non comune","immagine":"https://assets.tcgdex.net/it/swsh/swsh12.5/125"},{"numero":"126","nome":"Fratelli Vanghe in Spalla","categoria":"Allenatore","rarita":"Non comune","immagine":"https://assets.tcgdex.net/it/swsh/swsh12.5/126"},{"numero":"127","nome":"Recupero di Energia","categoria":"Allenatore","rarita":"Comune","immagine":"https://assets.tcgdex.net/it/swsh/swsh12.5/127"},{"numero":"128","nome":"Ricerca di Energia","categoria":"Allenatore","rarita":"Comune","immagine":"https://assets.tcgdex.net/it/swsh/swsh12.5/128"},{"numero":"129","nome":"Scambio di Energia","categoria":"Allenatore","rarita":"Non comune","immagine":"https://assets.tcgdex.net/it/swsh/swsh12.5/129"},{"numero":"130","nome":"Amici a Hisui","categoria":"Allenatore","rarita":"Non comune","immagine":"https://assets.tcgdex.net/it/swsh/swsh12.5/130"},{"numero":"131","nome":"Amici a Sinnoh","categoria":"Allenatore","rarita":"Non comune","immagine":"https://assets.tcgdex.net/it/swsh/swsh12.5/131"},{"numero":"132","nome":"Mega Ball","categoria":"Allenatore","rarita":"Non comune","immagine":"https://assets.tcgdex.net/it/swsh/swsh12.5/132"},{"numero":"133","nome":"Hop","categoria":"Allenatore","rarita":"Olografica Rara","immagine":"https://assets.tcgdex.net/it/swsh/swsh12.5/133"},{"numero":"134","nome":"Dandel","categoria":"Allenatore","rarita":"Olografica Rara","immagine":"https://assets.tcgdex.net/it/swsh/swsh12.5/134"},{"numero":"135","nome":"Aspiratore Perduto","categoria":"Allenatore","rarita":"Non comune","immagine":"https://assets.tcgdex.net/it/swsh/swsh12.5/135"},{"numero":"136","nome":"Azzurra","categoria":"Allenatore","rarita":"Olografica Rara","immagine":"https://assets.tcgdex.net/it/swsh/swsh12.5/136"},{"numero":"137","nome":"Poké Ball","categoria":"Allenatore","rarita":"Comune","immagine":"https://assets.tcgdex.net/it/swsh/swsh12.5/137"},{"numero":"138","nome":"Acchiappa-Pokémon","categoria":"Allenatore","rarita":"Non comune","immagine":"https://assets.tcgdex.net/it/swsh/swsh12.5/138"},{"numero":"139","nome":"Pozione","categoria":"Allenatore","rarita":"Comune","immagine":"https://assets.tcgdex.net/it/swsh/swsh12.5/139"},{"numero":"140","nome":"Laburno","categoria":"Allenatore","rarita":"Olografica Rara","immagine":"https://assets.tcgdex.net/it/swsh/swsh12.5/140"},{"numero":"141","nome":"Caramella Rara","categoria":"Allenatore","rarita":"Non comune","immagine":"https://assets.tcgdex.net/it/swsh/swsh12.5/141"},{"numero":"142","nome":"Trolley di Salvataggio","categoria":"Allenatore","rarita":"Non comune","immagine":"https://assets.tcgdex.net/it/swsh/swsh12.5/142"},{"numero":"143","nome":"Sigillo Celeste","categoria":"Allenatore","rarita":"Olografica Rara","immagine":"https://assets.tcgdex.net/it/swsh/swsh12.5/143"},{"numero":"144","nome":"Scambio","categoria":"Allenatore","rarita":"Comune","immagine":"https://assets.tcgdex.net/it/swsh/swsh12.5/144"},{"numero":"145","nome":"Scarpe da trekking","categoria":"Allenatore","rarita":"Non comune","immagine":"https://assets.tcgdex.net/it/swsh/swsh12.5/145"},{"numero":"146","nome":"Ultra Ball","categoria":"Allenatore","rarita":"Non comune","immagine":"https://assets.tcgdex.net/it/swsh/swsh12.5/146"},{"numero":"147","nome":"Leggiadria di Camelia","categoria":"Allenatore","rarita":"Ultrarara","immagine":"https://assets.tcgdex.net/it/swsh/swsh12.5/147"},{"numero":"148","nome":"Amici a Hisui","categoria":"Allenatore","rarita":"Ultrarara","immagine":"https://assets.tcgdex.net/it/swsh/swsh12.5/148"},{"numero":"149","nome":"Amici a Sinnoh","categoria":"Allenatore","rarita":"Ultrarara","immagine":"https://assets.tcgdex.net/it/swsh/swsh12.5/149"},{"numero":"150","nome":"Ricerca Accademica","categoria":"Allenatore","rarita":"Ultrarara","immagine":"https://assets.tcgdex.net/it/swsh/swsh12.5/150"},{"numero":"151","nome":"Ethelo","categoria":"Allenatore","rarita":"Ultrarara","immagine":"https://assets.tcgdex.net/it/swsh/swsh12.5/151"},{"numero":"152","nome":"Energia Erba","categoria":"Energia","rarita":"Ultrarara","immagine":"https://assets.tcgdex.net/it/swsh/swsh12.5/152","tipoEnergia":"Base"},{"numero":"153","nome":"Energia Fuoco","categoria":"Energia","rarita":"Ultrarara","immagine":"https://assets.tcgdex.net/it/swsh/swsh12.5/153","tipoEnergia":"Base"},{"numero":"154","nome":"Energia Acqua","categoria":"Energia","rarita":"Ultrarara","immagine":"https://assets.tcgdex.net/it/swsh/swsh12.5/154","tipoEnergia":"Base"},{"numero":"155","nome":"Energia Lampo","categoria":"Energia","rarita":"Ultrarara","immagine":"https://assets.tcgdex.net/it/swsh/swsh12.5/155","tipoEnergia":"Base"},{"numero":"156","nome":"Energia Psiche","categoria":"Energia","rarita":"Ultrarara","immagine":"https://assets.tcgdex.net/it/swsh/swsh12.5/156","tipoEnergia":"Base"},{"numero":"157","nome":"Energia Combattimento","categoria":"Energia","rarita":"Ultrarara","immagine":"https://assets.tcgdex.net/it/swsh/swsh12.5/157","tipoEnergia":"Base"},{"numero":"158","nome":"Energia Oscurità","categoria":"Energia","rarita":"Ultrarara","immagine":"https://assets.tcgdex.net/it/swsh/swsh12.5/158","tipoEnergia":"Base"},{"numero":"159","nome":"Energia Metallo","categoria":"Energia","rarita":"Ultrarara","immagine":"https://assets.tcgdex.net/it/swsh/swsh12.5/159","tipoEnergia":"Base"},{"numero":"160","nome":"Pikachu","categoria":"Pokémon","rarita":"Segreto rara","immagine":"https://assets.tcgdex.net/it/swsh/swsh12.5/160","stadio":"Base","evolveDa":null,"tipi":["Lampo"],"ps":70,"ritirata":1,"attacchi":[{"nome":"Sprizzalampo","costo":["Lampo","Lampo","Incolore"],"danno":90}]}]}