{"id":"xy7","nome":"Antiche Origini","totaleUfficiale":98,"totaleConSegrete":101,"scaricatoIl":"2026-07-19","carte":[{"numero":"1","nome":"Oddish","categoria":"Pokémon","rarita":"Comune","immagine":"https://assets.tcgdex.net/it/xy/xy7/1","stadio":"Base","evolveDa":null,"tipi":["Erba"],"ps":50,"ritirata":1,"attacchi":[{"nome":"Inciampare","costo":["Erba"],"danno":"10+"}]},{"numero":"2","nome":"Gloom","categoria":"Pokémon","rarita":"Non comune","immagine":"https://assets.tcgdex.net/it/xy/xy7/2","stadio":"Livello 1","evolveDa":"Oddish","tipi":["Erba"],"ps":80,"ritirata":1,"attacchi":[{"nome":"Sbavare","costo":["Erba","Incolore"],"danno":30}]},{"numero":"3","nome":"Vileplume","categoria":"Pokémon","rarita":"Rara","immagine":"https://assets.tcgdex.net/it/xy/xy7/3","stadio":"Livello 2","evolveDa":"Gloom","tipi":["Erba"],"ps":130,"ritirata":3,"attacchi":[{"nome":"Solarraggio","costo":["Erba","Erba","Incolore"],"danno":70}]},{"numero":"4","nome":"Bellossom","categoria":"Pokémon","rarita":"Non comune","immagine":"https://assets.tcgdex.net/it/xy/xy7/4","stadio":"Livello 2","evolveDa":"Gloom","tipi":["Erba"],"ps":120,"ritirata":1,"attacchi":[{"nome":"Mulino","costo":["Erba"],"danno":20},{"nome":"Vortifiore","costo":["Erba","Incolore"],"danno":60}]},{"numero":"5","nome":"Spinarak","categoria":"Pokémon","rarita":"Comune","immagine":"https://assets.tcgdex.net/it/xy/xy7/5","stadio":"Base","evolveDa":null,"tipi":["Erba"],"ps":50,"ritirata":1,"attacchi":[{"nome":"Millebave","costo":["Incolore"],"danno":null}]},{"numero":"6","nome":"Ariados","categoria":"Pokémon","rarita":"Non comune","immagine":"https://assets.tcgdex.net/it/xy/xy7/6","stadio":"Livello 1","evolveDa":"Spinarak","tipi":["Erba"],"ps":70,"ritirata":1,"attacchi":[{"nome":"Isolamento","costo":["Erba","Incolore"],"danno":30}]},{"numero":"7","nome":"Sceptile EX","categoria":"Pokémon","rarita":"Ultrarara","immagine":"https://assets.tcgdex.net/it/xy/xy7/7","stadio":"Base","evolveDa":null,"tipi":["Erba"],"ps":170,"ritirata":1,"attacchi":[{"nome":"Sonnoveleno","costo":["Erba"],"danno":10},{"nome":"Artigli Invisibili","costo":["Erba","Incolore"],"danno":"60+"}]},{"numero":"8","nome":"M Sceptile EX","categoria":"Pokémon","rarita":"Ultrarara","immagine":"https://assets.tcgdex.net/it/xy/xy7/8","stadio":"MEGA","evolveDa":"Sceptile-EX","tipi":["Erba"],"ps":220,"ritirata":2,"attacchi":[{"nome":"Dentesciabola","costo":["Erba","Incolore"],"danno":100}]},{"numero":"9","nome":"Combee","categoria":"Pokémon","rarita":"Comune","immagine":"https://assets.tcgdex.net/it/xy/xy7/9","stadio":"Base","evolveDa":null,"tipi":["Erba"],"ps":40,"ritirata":1,"attacchi":[{"nome":"Coleomorso","costo":["Erba"],"danno":10}]},{"numero":"10","nome":"Vespiquen","categoria":"Pokémon","rarita":"Non comune","immagine":"https://assets.tcgdex.net/it/xy/xy7/10","stadio":"Livello 1","evolveDa":"Combee","tipi":["Erba"],"ps":90,"ritirata":0,"attacchi":[{"nome":"Raccolta Informazioni","costo":["Incolore"],"danno":10},{"nome":"Apevendetta","costo":["Incolore","Incolore"],"danno":"20+"}]},{"numero":"11","nome":"Vespiquen","categoria":"Pokémon","rarita":"Rara","immagine":"https://assets.tcgdex.net/it/xy/xy7/11","stadio":"Livello 1","evolveDa":"Combee","tipi":["Erba"],"ps":90,"ritirata":1,"attacchi":[{"nome":"Apeassorbi","costo":["Erba"],"danno":20},{"nome":"Sfuriate","costo":["Incolore","Incolore"],"danno":"30×"}]},{"numero":"12","nome":"Virizion","categoria":"Pokémon","rarita":"Rara","immagine":"https://assets.tcgdex.net/it/xy/xy7/12","stadio":"Base","evolveDa":null,"tipi":["Erba"],"ps":110,"ritirata":1,"attacchi":[{"nome":"Soccorso","costo":["Erba"],"danno":null},{"nome":"Contapremi","costo":["Erba","Erba"],"danno":"40+"}]},{"numero":"13","nome":"Flareon","categoria":"Pokémon","rarita":"Non comune","immagine":"https://assets.tcgdex.net/it/xy/xy7/13","stadio":"Livello 1","evolveDa":"Eevee","tipi":["Fuoco"],"ps":90,"ritirata":1,"attacchi":[{"nome":"Alitorovente","costo":["Fuoco","Incolore","Incolore"],"danno":"60+"}]},{"numero":"14","nome":"Entei","categoria":"Pokémon","rarita":"Rara","immagine":"https://assets.tcgdex.net/it/xy/xy7/14","stadio":"Base","evolveDa":null,"tipi":["Fuoco"],"ps":120,"ritirata":2,"attacchi":[{"nome":"Bruciaboato","costo":["Incolore"],"danno":null},{"nome":"Scontrardente","costo":["Fuoco","Fuoco"],"danno":"20+"}]},{"numero":"15","nome":"Entei","categoria":"Pokémon","rarita":"Rara","immagine":"https://assets.tcgdex.net/it/xy/xy7/15","stadio":"Base","evolveDa":null,"tipi":["Fuoco"],"ps":130,"ritirata":2,"attacchi":[{"nome":"Muro di Fuoco","costo":["Fuoco","Incolore"],"danno":30},{"nome":"Calorazione","costo":["Fuoco","Fuoco","Incolore","Incolore"],"danno":130}]},{"numero":"16","nome":"Larvesta","categoria":"Pokémon","rarita":"Comune","immagine":"https://assets.tcgdex.net/it/xy/xy7/16","stadio":"Base","evolveDa":null,"tipi":["Fuoco"],"ps":70,"ritirata":2,"attacchi":[{"nome":"Fuoco Continuo","costo":["Fuoco","Incolore"],"danno":30}]},{"numero":"17","nome":"Volcarona","categoria":"Pokémon","rarita":"Rara","immagine":"https://assets.tcgdex.net/it/xy/xy7/17","stadio":"Livello 1","evolveDa":"Larvesta","tipi":["Fuoco"],"ps":100,"ritirata":1,"attacchi":[{"nome":"Solarnascita","costo":["Incolore"],"danno":null},{"nome":"Lanciafiamme","costo":["Fuoco","Incolore"],"danno":60}]},{"numero":"18","nome":"Volcarona","categoria":"Pokémon","rarita":"Rara","immagine":"https://assets.tcgdex.net/it/xy/xy7/18","stadio":"Livello 1","evolveDa":"Larvesta","tipi":["Fuoco"],"ps":110,"ritirata":2,"attacchi":[{"nome":"Scagliardente","costo":["Fuoco"],"danno":"20+"},{"nome":"Girandola","costo":["Fuoco","Incolore","Incolore"],"danno":80}]},{"numero":"19","nome":"Magikarp","categoria":"Pokémon","rarita":"Comune","immagine":"https://assets.tcgdex.net/it/xy/xy7/19","stadio":"Base","evolveDa":null,"tipi":["Acqua"],"ps":30,"ritirata":1,"attacchi":[{"nome":"Epicosplash","costo":["Acqua"],"danno":30}]},{"numero":"20","nome":"Gyarados","categoria":"Pokémon","rarita":"Rara","immagine":"https://assets.tcgdex.net/it/xy/xy7/20","stadio":"Livello 1","evolveDa":"Magikarp","tipi":["Acqua"],"ps":130,"ritirata":3,"attacchi":[{"nome":"Miticosplash","costo":["Acqua","Incolore","Incolore"],"danno":80},{"nome":"Idrondata","costo":["Acqua","Incolore","Incolore","Incolore"],"danno":"90+"}]},{"numero":"21","nome":"Gyarados","categoria":"Pokémon","rarita":"Rara","immagine":"https://assets.tcgdex.net/it/xy/xy7/21","stadio":"Livello 1","evolveDa":"Magikarp","tipi":["Acqua"],"ps":130,"ritirata":3,"attacchi":[{"nome":"Super Rappresaglia","costo":["Incolore","Incolore"],"danno":"30+"},{"nome":"Colpo","costo":["Acqua","Acqua","Incolore","Incolore"],"danno":"100+"}]},{"numero":"22","nome":"Vaporeon","categoria":"Pokémon","rarita":"Non comune","immagine":"https://assets.tcgdex.net/it/xy/xy7/22","stadio":"Livello 1","evolveDa":"Eevee","tipi":["Acqua"],"ps":90,"ritirata":2,"attacchi":[{"nome":"Idrosplash","costo":["Acqua","Incolore","Incolore"],"danno":70}]},{"numero":"23","nome":"Relicanth","categoria":"Pokémon","rarita":"Comune","immagine":"https://assets.tcgdex.net/it/xy/xy7/23","stadio":"Base","evolveDa":null,"tipi":["Acqua"],"ps":90,"ritirata":1,"attacchi":[{"nome":"Sonda Abissale","costo":["Incolore"],"danno":null},{"nome":"Riduttore","costo":["Incolore","Incolore"],"danno":30}]},{"numero":"24","nome":"Regice","categoria":"Pokémon","rarita":"Rara","immagine":"https://assets.tcgdex.net/it/xy/xy7/24","stadio":"Base","evolveDa":null,"tipi":["Acqua"],"ps":120,"ritirata":3,"attacchi":[{"nome":"Geloraggio","costo":["Acqua","Incolore"],"danno":30},{"nome":"Crioscudo","costo":["Acqua","Incolore","Incolore"],"danno":70}]},{"numero":"25","nome":"Kyurem EX","categoria":"Pokémon","rarita":"Ultrarara","immagine":"https://assets.tcgdex.net/it/xy/xy7/25","stadio":"Base","evolveDa":null,"tipi":["Acqua"],"ps":180,"ritirata":3,"attacchi":[{"nome":"Gelamondo","costo":["Acqua","Acqua","Incolore"],"danno":null},{"nome":"Algicalibur","costo":["Acqua","Acqua","Acqua","Incolore"],"danno":130}]},{"numero":"26","nome":"Jolteon","categoria":"Pokémon","rarita":"Rara","immagine":"https://assets.tcgdex.net/it/xy/xy7/26","stadio":"Livello 1","evolveDa":"Eevee","tipi":["Lampo"],"ps":90,"ritirata":0,"attacchi":[{"nome":"Tuonobomba","costo":["Lampo","Incolore","Incolore"],"danno":80}]},{"numero":"27","nome":"Ampharos EX","categoria":"Pokémon","rarita":"Ultrarara","immagine":"https://assets.tcgdex.net/it/xy/xy7/27","stadio":"Base","evolveDa":null,"tipi":["Lampo"],"ps":170,"ritirata":2,"attacchi":[{"nome":"Elettrobolide","costo":["Incolore"],"danno":null},{"nome":"Luminocoda","costo":["Lampo","Lampo","Incolore","Incolore"],"danno":100}]},{"numero":"28","nome":"M Ampharos EX","categoria":"Pokémon","rarita":"Ultrarara","immagine":"https://assets.tcgdex.net/it/xy/xy7/28","stadio":"MEGA","evolveDa":"Ampharos-EX","tipi":["Lampo"],"ps":220,"ritirata":3,"attacchi":[{"nome":"Exavolt","costo":["Lampo","Lampo","Incolore","Incolore"],"danno":"120+"}]},{"numero":"29","nome":"Rotom","categoria":"Pokémon","rarita":"Non comune","immagine":"https://assets.tcgdex.net/it/xy/xy7/29","stadio":"Base","evolveDa":null,"tipi":["Lampo"],"ps":70,"ritirata":1,"attacchi":[{"nome":"Energisfera","costo":["Lampo"],"danno":20},{"nome":"Elettroburla","costo":["Incolore","Incolore"],"danno":null}]},{"numero":"30","nome":"Unown","categoria":"Pokémon","rarita":"Comune","immagine":"https://assets.tcgdex.net/it/xy/xy7/30","stadio":"Base","evolveDa":null,"tipi":["Psico"],"ps":60,"ritirata":1,"attacchi":[{"nome":"Introforza","costo":["Incolore"],"danno":10}]},{"numero":"31","nome":"Baltoy","categoria":"Pokémon","rarita":"Comune","immagine":"https://assets.tcgdex.net/it/xy/xy7/31","stadio":"Base","evolveDa":null,"tipi":["Psico"],"ps":60,"ritirata":1,"attacchi":[{"nome":"Sberla","costo":["Psico"],"danno":10},{"nome":"Attacco Rotante","costo":["Psico","Incolore"],"danno":20}]},{"numero":"32","nome":"Baltoy","categoria":"Pokémon","rarita":"Comune","immagine":"https://assets.tcgdex.net/it/xy/xy7/32","stadio":"Base","evolveDa":null,"tipi":["Psico"],"ps":60,"ritirata":1,"attacchi":[{"nome":"Volgifuturo","costo":["Psico"],"danno":null}]},{"numero":"33","nome":"Claydol","categoria":"Pokémon","rarita":"Rara","immagine":"https://assets.tcgdex.net/it/xy/xy7/33","stadio":"Livello 1","evolveDa":"Baltoy","tipi":["Psico"],"ps":100,"ritirata":2,"attacchi":[{"nome":"Riavvolgi","costo":["Psico"],"danno":null},{"nome":"Iper Raggio","costo":["Psico","Incolore"],"danno":30}]},{"numero":"34","nome":"Golett","categoria":"Pokémon","rarita":"Comune","immagine":"https://assets.tcgdex.net/it/xy/xy7/34","stadio":"Base","evolveDa":null,"tipi":["Psico"],"ps":90,"ritirata":3,"attacchi":[{"nome":"Devastapugno","costo":["Incolore","Incolore"],"danno":30}]},{"numero":"35","nome":"Golurk","categoria":"Pokémon","rarita":"Rara","immagine":"https://assets.tcgdex.net/it/xy/xy7/35","stadio":"Livello 1","evolveDa":"Golett","tipi":["Psico"],"ps":130,"ritirata":4,"attacchi":[{"nome":"Troppoforte","costo":["Incolore","Incolore","Incolore","Incolore"],"danno":"80+"}]},{"numero":"36","nome":"Hoopa EX","categoria":"Pokémon","rarita":"Ultrarara","immagine":"https://assets.tcgdex.net/it/xy/xy7/36","stadio":"Base","evolveDa":null,"tipi":["Psico"],"ps":170,"ritirata":2,"attacchi":[{"nome":"Urtodimensionale","costo":["Psico","Psico","Psico"],"danno":null}]},{"numero":"37","nome":"Machamp EX","categoria":"Pokémon","rarita":"Ultrarara","immagine":"https://assets.tcgdex.net/it/xy/xy7/37","stadio":"Base","evolveDa":null,"tipi":["Lotta"],"ps":180,"ritirata":3,"attacchi":[{"nome":"Escandescenza","costo":["Lotta","Incolore"],"danno":"20×"},{"nome":"Martelpazzo","costo":["Lotta","Lotta","Incolore"],"danno":"80+"}]},{"numero":"38","nome":"Wooper","categoria":"Pokémon","rarita":"Comune","immagine":"https://assets.tcgdex.net/it/xy/xy7/38","stadio":"Base","evolveDa":null,"tipi":["Lotta"],"ps":60,"ritirata":2,"attacchi":[{"nome":"Pausa","costo":["Incolore"],"danno":null},{"nome":"Schizzi d'Onda","costo":["Acqua","Incolore"],"danno":20}]},{"numero":"39","nome":"Quagsire","categoria":"Pokémon","rarita":"Comune","immagine":"https://assets.tcgdex.net/it/xy/xy7/39","stadio":"Livello 1","evolveDa":"Wooper","tipi":["Lotta"],"ps":110,"ritirata":3,"attacchi":[{"nome":"Schizzi d'Onda","costo":["Acqua","Incolore"],"danno":30},{"nome":"Sconquasso","costo":["Acqua","Incolore","Incolore"],"danno":80}]},{"numero":"40","nome":"Regirock","categoria":"Pokémon","rarita":"Rara","immagine":"https://assets.tcgdex.net/it/xy/xy7/40","stadio":"Base","evolveDa":null,"tipi":["Lotta"],"ps":120,"ritirata":3,"attacchi":[{"nome":"Sassata","costo":["Lotta","Incolore"],"danno":40},{"nome":"Saldaroccia","costo":["Lotta","Incolore","Incolore"],"danno":"60+"}]},{"numero":"41","nome":"Golurk","categoria":"Pokémon","rarita":"Comune","immagine":"https://assets.tcgdex.net/it/xy/xy7/41","stadio":"Livello 1","evolveDa":"Golett","tipi":["Lotta"],"ps":130,"ritirata":4,"attacchi":[{"nome":"Scavata","costo":["Incolore"],"danno":20},{"nome":"Doppio Lazzo","costo":["Lotta","Incolore","Incolore","Incolore"],"danno":"90×"}]},{"numero":"42","nome":"Tyranitar EX","categoria":"Pokémon","rarita":"Ultrarara","immagine":"https://assets.tcgdex.net/it/xy/xy7/42","stadio":"Base","evolveDa":null,"tipi":["Oscurità"],"ps":180,"ritirata":4,"attacchi":[{"nome":"Martello","costo":["Oscurità","Incolore","Incolore"],"danno":60},{"nome":"Distruggiterra","costo":["Oscurità","Oscurità","Incolore","Incolore"],"danno":130}]},{"numero":"43","nome":"M Tyranitar EX","categoria":"Pokémon","rarita":"Ultrarara","immagine":"https://assets.tcgdex.net/it/xy/xy7/43","stadio":"MEGA","evolveDa":"Tyranitar-EX","tipi":["Oscurità"],"ps":240,"ritirata":4,"attacchi":[{"nome":"Distruttore Assoluto","costo":["Oscurità","Oscurità","Incolore","Incolore"],"danno":"110+"}]},{"numero":"44","nome":"Sableye","categoria":"Pokémon","rarita":"Non comune","immagine":"https://assets.tcgdex.net/it/xy/xy7/44","stadio":"Base","evolveDa":null,"tipi":["Oscurità"],"ps":70,"ritirata":1,"attacchi":[{"nome":"Ammaliasguardo","costo":["Oscurità"],"danno":null},{"nome":"Lascito Furtivo","costo":["Oscurità","Incolore"],"danno":null}]},{"numero":"45","nome":"Inkay","categoria":"Pokémon","rarita":"Comune","immagine":"https://assets.tcgdex.net/it/xy/xy7/45","stadio":"Base","evolveDa":null,"tipi":["Oscurità"],"ps":50,"ritirata":1,"attacchi":[{"nome":"Sputinchiostro","costo":["Oscurità"],"danno":10}]},{"numero":"46","nome":"Malamar","categoria":"Pokémon","rarita":"Comune","immagine":"https://assets.tcgdex.net/it/xy/xy7/46","stadio":"Livello 1","evolveDa":"Inkay","tipi":["Oscurità"],"ps":90,"ritirata":1,"attacchi":[{"nome":"Invischiacomando","costo":["Incolore"],"danno":null},{"nome":"Scartatentacolo","costo":["Oscurità"],"danno":30}]},{"numero":"47","nome":"Beldum","categoria":"Pokémon","rarita":"Comune","immagine":"https://assets.tcgdex.net/it/xy/xy7/47","stadio":"Base","evolveDa":null,"tipi":["Metallo"],"ps":60,"ritirata":2,"attacchi":[{"nome":"Carica","costo":["Metallo"],"danno":10},{"nome":"Attacco Rotante","costo":["Metallo","Incolore","Incolore"],"danno":30}]},{"numero":"48","nome":"Metang","categoria":"Pokémon","rarita":"Non comune","immagine":"https://assets.tcgdex.net/it/xy/xy7/48","stadio":"Livello 1","evolveDa":"Beldum","tipi":["Metallo"],"ps":90,"ritirata":3,"attacchi":[{"nome":"Ferrartigli","costo":["Metallo","Incolore"],"danno":30},{"nome":"Pugnoscarica","costo":["Metallo","Metallo","Incolore"],"danno":"50+"}]},{"numero":"49","nome":"Metagross","categoria":"Pokémon","rarita":"Rara","immagine":"https://assets.tcgdex.net/it/xy/xy7/49","stadio":"Livello 2","evolveDa":"Metang","tipi":["Metallo"],"ps":150,"ritirata":4,"attacchi":[{"nome":"Metalcannone","costo":["Metallo","Metallo","Incolore","Incolore"],"danno":"80+"}]},{"numero":"50","nome":"Metagross","categoria":"Pokémon","rarita":"Rara","immagine":"https://assets.tcgdex.net/it/xy/xy7/50","stadio":"Livello 2","evolveDa":"Metang","tipi":["Metallo"],"ps":150,"ritirata":4,"attacchi":[{"nome":"Pestata Mitra","costo":["Incolore","Incolore"],"danno":"20+"},{"nome":"Pressadifesa","costo":["Metallo","Metallo","Incolore","Incolore"],"danno":80}]},{"numero":"51","nome":"Registeel","categoria":"Pokémon","rarita":"Rara","immagine":"https://assets.tcgdex.net/it/xy/xy7/51","stadio":"Base","evolveDa":null,"tipi":["Metallo"],"ps":120,"ritirata":3,"attacchi":[{"nome":"Metaltestata","costo":["Metallo","Incolore"],"danno":"30×"},{"nome":"Fantamartello Metallico","costo":["Metallo","Incolore","Incolore"],"danno":70}]},{"numero":"52","nome":"Ralts","categoria":"Pokémon","rarita":"Comune","immagine":"https://assets.tcgdex.net/it/xy/xy7/52","stadio":"Base","evolveDa":null,"tipi":["Folletto"],"ps":60,"ritirata":1,"attacchi":[{"nome":"Borbottio","costo":["Incolore"],"danno":10},{"nome":"Magicolpo","costo":["Folletto","Incolore"],"danno":20}]},{"numero":"53","nome":"Kirlia","categoria":"Pokémon","rarita":"Non comune","immagine":"https://assets.tcgdex.net/it/xy/xy7/53","stadio":"Livello 1","evolveDa":"Ralts","tipi":["Folletto"],"ps":80,"ritirata":1,"attacchi":[{"nome":"Calmamente","costo":["Incolore"],"danno":null},{"nome":"Magicolpo","costo":["Folletto","Incolore","Incolore"],"danno":50}]},{"numero":"54","nome":"Gardevoir","categoria":"Pokémon","rarita":"Rara","immagine":"https://assets.tcgdex.net/it/xy/xy7/54","stadio":"Livello 2","evolveDa":"Kirlia","tipi":["Folletto"],"ps":130,"ritirata":2,"attacchi":[{"nome":"Telecinesi","costo":["Incolore","Incolore","Incolore"],"danno":null}]},{"numero":"55","nome":"Cottonee","categoria":"Pokémon","rarita":"Comune","immagine":"https://assets.tcgdex.net/it/xy/xy7/55","stadio":"Base","evolveDa":null,"tipi":["Folletto"],"ps":40,"ritirata":1,"attacchi":[{"nome":"Cotonsonno","costo":["Folletto"],"danno":10}]},{"numero":"56","nome":"Whimsicott","categoria":"Pokémon","rarita":"Non comune","immagine":"https://assets.tcgdex.net/it/xy/xy7/56","stadio":"Livello 1","evolveDa":"Cottonee","tipi":["Folletto"],"ps":70,"ritirata":1,"attacchi":[{"nome":"Vento Birichino","costo":["Folletto"],"danno":null},{"nome":"Rollazione","costo":["Incolore","Incolore"],"danno":30}]},{"numero":"57","nome":"Giratina EX","categoria":"Pokémon","rarita":"Ultrarara","immagine":"https://assets.tcgdex.net/it/xy/xy7/57","stadio":"Base","evolveDa":null,"tipi":["Drago"],"ps":170,"ritirata":3,"attacchi":[{"nome":"Ruotacaos","costo":["Erba","Psico","Incolore","Incolore"],"danno":100}]},{"numero":"58","nome":"Goomy","categoria":"Pokémon","rarita":"Comune","immagine":"https://assets.tcgdex.net/it/xy/xy7/58","stadio":"Base","evolveDa":null,"tipi":["Drago"],"ps":40,"ritirata":2,"attacchi":[{"nome":"Fuggi Fuggi","costo":["Folletto","Incolore"],"danno":10}]},{"numero":"59","nome":"Sliggoo","categoria":"Pokémon","rarita":"Non comune","immagine":"https://assets.tcgdex.net/it/xy/xy7/59","stadio":"Livello 1","evolveDa":"Goomy","tipi":["Drago"],"ps":70,"ritirata":3,"attacchi":[{"nome":"Bolla","costo":["Incolore"],"danno":null},{"nome":"Liquefazione","costo":["Acqua","Folletto"],"danno":20}]},{"numero":"60","nome":"Goodra","categoria":"Pokémon","rarita":"Rara","immagine":"https://assets.tcgdex.net/it/xy/xy7/60","stadio":"Livello 2","evolveDa":"Sliggoo","tipi":["Drago"],"ps":150,"ritirata":3,"attacchi":[{"nome":"Colpofluido","costo":["Incolore","Incolore"],"danno":null},{"nome":"Spirolucente","costo":["Acqua","Folletto","Incolore","Incolore"],"danno":110}]},{"numero":"61","nome":"Meowth","categoria":"Pokémon","rarita":"Comune","immagine":"https://assets.tcgdex.net/it/xy/xy7/61","stadio":"Base","evolveDa":null,"tipi":["Incolore"],"ps":60,"ritirata":1,"attacchi":[{"nome":"Fatti Miei","costo":["Incolore"],"danno":"10+"}]},{"numero":"62","nome":"Persian","categoria":"Pokémon","rarita":"Comune","immagine":"https://assets.tcgdex.net/it/xy/xy7/62","stadio":"Livello 1","evolveDa":"Meowth","tipi":["Incolore"],"ps":90,"ritirata":1,"attacchi":[{"nome":"Bruciapelo","costo":["Incolore"],"danno":30},{"nome":"Imboscata","costo":["Incolore","Incolore"],"danno":"40+"}]},{"numero":"63","nome":"Eevee","categoria":"Pokémon","rarita":"Comune","immagine":"https://assets.tcgdex.net/it/xy/xy7/63","stadio":"Base","evolveDa":null,"tipi":["Incolore"],"ps":60,"ritirata":1,"attacchi":[{"nome":"Azione","costo":["Incolore"],"danno":10},{"nome":"Affondo","costo":["Incolore","Incolore"],"danno":30}]},{"numero":"64","nome":"Porygon","categoria":"Pokémon","rarita":"Comune","immagine":"https://assets.tcgdex.net/it/xy/xy7/64","stadio":"Base","evolveDa":null,"tipi":["Incolore"],"ps":60,"ritirata":1,"attacchi":[{"nome":"Controllo Dati","costo":["Incolore"],"danno":null},{"nome":"Affilatore","costo":["Incolore","Incolore"],"danno":20}]},{"numero":"65","nome":"Porygon2","categoria":"Pokémon","rarita":"Non comune","immagine":"https://assets.tcgdex.net/it/xy/xy7/65","stadio":"Livello 1","evolveDa":"Porygon","tipi":["Incolore"],"ps":80,"ritirata":2,"attacchi":[{"nome":"Affilatore","costo":["Incolore"],"danno":20},{"nome":"Tripletta","costo":["Incolore","Incolore","Incolore"],"danno":"30×"}]},{"numero":"66","nome":"Porygon-Z","categoria":"Pokémon","rarita":"Rara","immagine":"https://assets.tcgdex.net/it/xy/xy7/66","stadio":"Livello 2","evolveDa":"Porygon2","tipi":["Incolore"],"ps":130,"ritirata":2,"attacchi":[{"nome":"Schianto Cibernetico","costo":["Incolore"],"danno":null},{"nome":"Frenoraggio","costo":["Incolore","Incolore","Incolore"],"danno":70}]},{"numero":"67","nome":"Porygon-Z","categoria":"Pokémon","rarita":"Rara","immagine":"https://assets.tcgdex.net/it/xy/xy7/67","stadio":"Livello 2","evolveDa":"Porygon2","tipi":["Incolore"],"ps":130,"ritirata":2,"attacchi":[{"nome":"Riavvio Digitale","costo":["Incolore"],"danno":null},{"nome":"Accecobomba","costo":["Incolore","Incolore"],"danno":50}]},{"numero":"68","nome":"Lugia EX","categoria":"Pokémon","rarita":"Ultrarara","immagine":"https://assets.tcgdex.net/it/xy/xy7/68","stadio":"Base","evolveDa":null,"tipi":["Incolore"],"ps":170,"ritirata":2,"attacchi":[{"nome":"Aerosfera","costo":["Incolore","Incolore"],"danno":"20×"},{"nome":"Uragano Abissale","costo":["Incolore","Incolore","Incolore","Incolore"],"danno":"80+"}]},{"numero":"69","nome":"Fantallenatori","categoria":"Allenatore","rarita":"Non comune","immagine":"https://assets.tcgdex.net/it/xy/xy7/69"},{"numero":"70","nome":"Legame Mentale con Ampharos","categoria":"Allenatore","rarita":"Non comune","immagine":"https://assets.tcgdex.net/it/xy/xy7/70"},{"numero":"71","nome":"Braccio Ecologico","categoria":"Allenatore","rarita":"Non comune","immagine":"https://assets.tcgdex.net/it/xy/xy7/71"},{"numero":"72","nome":"Riciclaggio di Energia","categoria":"Allenatore","rarita":"Non comune","immagine":"https://assets.tcgdex.net/it/xy/xy7/72"},{"numero":"73","nome":"Città Deserta","categoria":"Allenatore","rarita":"Non comune","immagine":"https://assets.tcgdex.net/it/xy/xy7/73"},{"numero":"74","nome":"Foresta delle Piante Giganti","categoria":"Allenatore","rarita":"Non comune","immagine":"https://assets.tcgdex.net/it/xy/xy7/74"},{"numero":"75a","nome":"Streghetta","categoria":"Allenatore","rarita":"Non comune","immagine":"https://assets.tcgdex.net/it/xy/xy7/75a"},{"numero":"75","nome":"Streghetta","categoria":"Allenatore","rarita":"Non comune","immagine":"https://assets.tcgdex.net/it/xy/xy7/75"},{"numero":"76","nome":"Level Ball","categoria":"Allenatore","rarita":"Non comune","immagine":"https://assets.tcgdex.net/it/xy/xy7/76"},{"numero":"77","nome":"Fortunelmo","categoria":"Allenatore","rarita":"Non comune","immagine":"https://assets.tcgdex.net/it/xy/xy7/77"},{"numero":"78","nome":"Elisio","categoria":"Allenatore","rarita":"Non comune","immagine":"https://assets.tcgdex.net/it/xy/xy7/78"},{"numero":"79","nome":"Imbiancarullo","categoria":"Allenatore","rarita":"Non comune","immagine":"https://assets.tcgdex.net/it/xy/xy7/79"},{"numero":"80","nome":"Legame Mentale con Sceptile","categoria":"Allenatore","rarita":"Non comune","immagine":"https://assets.tcgdex.net/it/xy/xy7/80"},{"numero":"81","nome":"Legame Mentale con Tyranitar","categoria":"Allenatore","rarita":"Non comune","immagine":"https://assets.tcgdex.net/it/xy/xy7/81"},{"numero":"82","nome":"Energia Pericolo","categoria":"Energia","rarita":"Non comune","immagine":"https://assets.tcgdex.net/it/xy/xy7/82","tipoEnergia":"Speciale"},{"numero":"83","nome":"Energia Flash","categoria":"Energia","rarita":"Non comune","immagine":"https://assets.tcgdex.net/it/xy/xy7/83","tipoEnergia":"Speciale"},{"numero":"84","nome":"Sceptile EX","categoria":"Pokémon","rarita":"Ultrarara","immagine":"https://assets.tcgdex.net/it/xy/xy7/84","stadio":"Base","evolveDa":null,"tipi":["Erba"],"ps":170,"ritirata":1,"attacchi":[{"nome":"Sonnoveleno","costo":["Erba"],"danno":10},{"nome":"Artigli Invisibili","costo":["Erba","Incolore"],"danno":"60+"}]},{"numero":"85","nome":"M Sceptile EX","categoria":"Pokémon","rarita":"Ultrarara","immagine":"https://assets.tcgdex.net/it/xy/xy7/85","stadio":"MEGA","evolveDa":"Sceptile-EX","tipi":["Erba"],"ps":220,"ritirata":2,"attacchi":[{"nome":"Dentesciabola","costo":["Erba","Incolore"],"danno":100}]},{"numero":"86","nome":"Kyurem EX","categoria":"Pokémon","rarita":"Ultrarara","immagine":"https://assets.tcgdex.net/it/xy/xy7/86","stadio":"Base","evolveDa":null,"tipi":["Acqua"],"ps":180,"ritirata":3,"attacchi":[{"nome":"Gelamondo","costo":["Acqua","Acqua","Incolore"],"danno":null},{"nome":"Algicalibur","costo":["Acqua","Acqua","Acqua","Incolore"],"danno":130}]},{"numero":"87","nome":"Ampharos EX","categoria":"Pokémon","rarita":"Ultrarara","immagine":"https://assets.tcgdex.net/it/xy/xy7/87","stadio":"Base","evolveDa":null,"tipi":["Lampo"],"ps":170,"ritirata":2,"attacchi":[{"nome":"Elettrobolide","costo":["Incolore"],"danno":null},{"nome":"Luminocoda","costo":["Lampo","Lampo","Incolore","Incolore"],"danno":100}]},{"numero":"88","nome":"M Ampharos EX","categoria":"Pokémon","rarita":"Ultrarara","immagine":"https://assets.tcgdex.net/it/xy/xy7/88","stadio":"MEGA","evolveDa":"Ampharos-EX","tipi":["Lampo"],"ps":220,"ritirata":3,"attacchi":[{"nome":"Exavolt","costo":["Lampo","Lampo","Incolore","Incolore"],"danno":"120+"}]},{"numero":"89","nome":"Hoopa EX","categoria":"Pokémon","rarita":"Ultrarara","immagine":"https://assets.tcgdex.net/it/xy/xy7/89","stadio":"Base","evolveDa":null,"tipi":["Psico"],"ps":170,"ritirata":2,"attacchi":[{"nome":"Urtodimensionale","costo":["Psico","Psico","Psico"],"danno":null}]},{"numero":"90","nome":"Machamp EX","categoria":"Pokémon","rarita":"Ultrarara","immagine":"https://assets.tcgdex.net/it/xy/xy7/90","stadio":"Base","evolveDa":null,"tipi":["Lotta"],"ps":180,"ritirata":3,"attacchi":[{"nome":"Escandescenza","costo":["Lotta","Incolore"],"danno":"20×"},{"nome":"Martelpazzo","costo":["Lotta","Lotta","Incolore"],"danno":"80+"}]},{"numero":"91","nome":"Tyranitar EX","categoria":"Pokémon","rarita":"Ultrarara","immagine":"https://assets.tcgdex.net/it/xy/xy7/91","stadio":"Base","evolveDa":null,"tipi":["Oscurità"],"ps":180,"ritirata":4,"attacchi":[{"nome":"Martello","costo":["Oscurità","Incolore","Incolore"],"danno":60},{"nome":"Distruggiterra","costo":["Oscurità","Oscurità","Incolore","Incolore"],"danno":130}]},{"numero":"92","nome":"M Tyranitar EX","categoria":"Pokémon","rarita":"Ultrarara","immagine":"https://assets.tcgdex.net/it/xy/xy7/92","stadio":"MEGA","evolveDa":"Tyranitar-EX","tipi":["Oscurità"],"ps":240,"ritirata":4,"attacchi":[{"nome":"Distruttore Assoluto","costo":["Oscurità","Oscurità","Incolore","Incolore"],"danno":"110+"}]},{"numero":"93","nome":"Giratina EX","categoria":"Pokémon","rarita":"Ultrarara","immagine":"https://assets.tcgdex.net/it/xy/xy7/93","stadio":"Base","evolveDa":null,"tipi":["Drago"],"ps":170,"ritirata":3,"attacchi":[{"nome":"Ruotacaos","costo":["Erba","Psico","Incolore","Incolore"],"danno":100}]},{"numero":"94","nome":"Lugia EX","categoria":"Pokémon","rarita":"Ultrarara","immagine":"https://assets.tcgdex.net/it/xy/xy7/94","stadio":"Base","evolveDa":null,"tipi":["Incolore"],"ps":170,"ritirata":2,"attacchi":[{"nome":"Aerosfera","costo":["Incolore","Incolore"],"danno":"20×"},{"nome":"Uragano Abissale","costo":["Incolore","Incolore","Incolore","Incolore"],"danno":"80+"}]},{"numero":"95","nome":"Rocco","categoria":"Allenatore","rarita":"Ultrarara","immagine":"https://assets.tcgdex.net/it/xy/xy7/95"},{"numero":"96","nome":"Archeo Kyogre EX","categoria":"Pokémon","rarita":"Segreto rara","immagine":"https://assets.tcgdex.net/it/xy/xy7/96","stadio":"MEGA","evolveDa":"Kyogre-EX","tipi":["Acqua"],"ps":240,"ritirata":4,"attacchi":[{"nome":"Tempesta Marina","costo":["Acqua","Acqua","Acqua","Incolore"],"danno":150}]},{"numero":"97","nome":"Archeo Groudon EX","categoria":"Pokémon","rarita":"Segreto rara","immagine":"https://assets.tcgdex.net/it/xy/xy7/97","stadio":"MEGA","evolveDa":"Groudon-EX","tipi":["Lotta"],"ps":240,"ritirata":4,"attacchi":[{"nome":"Vulcano Gaia","costo":["Lotta","Lotta","Lotta","Incolore"],"danno":"100+"}]},{"numero":"98","nome":"M Rayquaza EX","categoria":"Pokémon","rarita":"Segreto rara","immagine":"https://assets.tcgdex.net/it/xy/xy7/98","stadio":"MEGA","evolveDa":"Rayquaza-EX","tipi":["Incolore"],"ps":220,"ritirata":1,"attacchi":[{"nome":"Colposmeraldo","costo":["Incolore","Incolore","Incolore"],"danno":"30×"}]},{"numero":"99","nome":"Recupero di Energia","categoria":"Allenatore","rarita":"Segreto rara","immagine":"https://assets.tcgdex.net/it/xy/xy7/99"},{"numero":"100","nome":"Posta Allenatori","categoria":"Allenatore","rarita":"Segreto rara","immagine":"https://assets.tcgdex.net/it/xy/xy7/100"}]}